terraval/__init__.py
terraval/terraval.py
terraval-0.0.1.dist-info/METADATA
terraval-0.0.1.dist-info/WHEEL
terraval-0.0.1.dist-info/top_level.txt
terraval-0.0.1.dist-info/RECORD
