Metadata-Version: 2.1
Name: terraval
Version: 0.0.1
Summary: A Python module for Terraform validation
Home-page: UNKNOWN
Author: M. Vidyaa Shankar
License: UNKNOWN
Platform: UNKNOWN
